django_smoke_tests/__init__.py
django_smoke_tests/apps.py
django_smoke_tests/generator.py
django_smoke_tests/migrations.py
django_smoke_tests/runners.py
django_smoke_tests/tests.py
django_smoke_tests/management/__init__.py
django_smoke_tests/management/commands/__init__.py
django_smoke_tests/management/commands/smoke_tests.py
django_smoke_tests/static/css/django_smoke_tests.css
django_smoke_tests/static/js/django_smoke_tests.js
django_smoke_tests/templates/django_smoke_tests/base.html
django_smoke_tests-0.4.1.dist-info/DESCRIPTION.rst
django_smoke_tests-0.4.1.dist-info/METADATA
django_smoke_tests-0.4.1.dist-info/RECORD
django_smoke_tests-0.4.1.dist-info/WHEEL
django_smoke_tests-0.4.1.dist-info/metadata.json
django_smoke_tests-0.4.1.dist-info/top_level.txt
