Metadata-Version: 2.0
Name: django-smoke-tests
Version: 0.4.1
Summary: Automatic smoke tests for Django project.
Home-page: https://github.com/kamilkijak/django-smoke-tests
Author: Kamil Kijak
Author-email: kamilkijak@gmail.com
License: MIT
Keywords: django-smoke-tests,test,smoke
Platform: UNKNOWN
Classifier: Development Status :: 3 - Alpha
Classifier: Framework :: Django
Classifier: Framework :: Django :: 1.8
Classifier: Framework :: Django :: 1.9
Classifier: Framework :: Django :: 1.10
Classifier: Framework :: Django :: 1.11
Classifier: Intended Audience :: Developers
Classifier: License :: OSI Approved :: BSD License
Classifier: Natural Language :: English
Classifier: Programming Language :: Python :: 2
Classifier: Programming Language :: Python :: 2.7
Classifier: Programming Language :: Python :: 3
Classifier: Programming Language :: Python :: 3.4
Classifier: Programming Language :: Python :: 3.5
Classifier: Programming Language :: Python :: 3.6
